wikit_chatintents/__init__.py
wikit_chatintents/wikit_chatintents.py
wikit_chatintents-0.0.5.dist-info/LICENSE
wikit_chatintents-0.0.5.dist-info/METADATA
wikit_chatintents-0.0.5.dist-info/WHEEL
wikit_chatintents-0.0.5.dist-info/top_level.txt
wikit_chatintents-0.0.5.dist-info/RECORD
