Metadata-Version: 2.1
Name: wikit-chatintents
Version: 0.0.5
Summary: ChatIntents automatically clusters and labels short text intent messages. Spacy model changed from english to french.
Home-page: https://github.com/dborrelli/chat-intents
Author: Wikit
Keywords: nlp clustering document embeddings unsupervised intents
Classifier: Programming Language :: Python :: 3
Classifier: License :: OSI Approved :: MIT License
Classifier: Operating System :: OS Independent
Requires-Python: >=3.9
License-File: LICENSE
Requires-Dist: numpy (>=1.19.2)
Requires-Dist: pandas (>=1.2.0)
Requires-Dist: umap-learn (>=0.5.1)
Requires-Dist: hdbscan (>=0.8.27)
Requires-Dist: hyperopt (>=0.2.5)
Requires-Dist: matplotlib (>=3.4.2)
Requires-Dist: spacy (>=3.1.2)
Requires-Dist: ipywidgets (>=7.6.3)
